Metadata-Version: 1.1
Name: markdown-djangostaticimage
Version: 0.1
Summary: Markdown extension: Add static tag to image source
Home-page: https://bitbucket.org/melvinkcx/markdown-extension-django-static-image
Author: Melvin Koh
Author-email: melvinkcx@gmail.com
License: MIT
Keywords: django markdown static html text filter
Platform: UNKNOWN
Classifier: Development Status :: 5 - Production/Stable
Classifier: Environment :: Console
Classifier: Intended Audience :: Developers
Classifier: Operating System :: OS Independent
Classifier: Topic :: Software Development :: Libraries :: Python Modules
Classifier: Topic :: Text Processing :: Filters
Classifier: Topic :: Text Processing :: Markup :: HTML
Classifier: Programming Language :: Python :: 2
Classifier: Programming Language :: Python :: 2.6
Classifier: Programming Language :: Python :: 2.7
Classifier: Programming Language :: Python :: 3
Classifier: Programming Language :: Python :: 3.3
Classifier: Programming Language :: Python :: 3.4
Classifier: Programming Language :: Python :: 3.5
Classifier: Programming Language :: Python :: 3.6
